colourful/__init__.py
colourful-1.2.5.dist-info/LICENSE.txt
colourful-1.2.5.dist-info/METADATA
colourful-1.2.5.dist-info/WHEEL
colourful-1.2.5.dist-info/top_level.txt
colourful-1.2.5.dist-info/RECORD
