Metadata-Version: 2.1
Name: colourful
Version: 1.2.5
Summary: colourful is a package to colorize any greyscale image.
Home-page: https://github.com/toxicrecker/colourful
Author: toxicrecker
Author-email: reck.channel.mainlead@gmail.com
License: UNKNOWN
Platform: UNKNOWN
Classifier: Programming Language :: Python :: 3
Classifier: License :: OSI Approved :: MIT License
Classifier: Operating System :: OS Independent
Requires-Python: >=3.6
